fastapi_google_iap/__init__.py
fastapi_google_iap/google_iap_middleware.py
fastapi_google_iap-1.0.1.dist-info/LICENSE
fastapi_google_iap-1.0.1.dist-info/METADATA
fastapi_google_iap-1.0.1.dist-info/WHEEL
fastapi_google_iap-1.0.1.dist-info/top_level.txt
fastapi_google_iap-1.0.1.dist-info/RECORD
