Metadata-Version: 2.1
Name: fastapi-google-iap
Version: 1.0.1
Summary: Middleware for FastAPI/Starlette to check requests coming through Google Cloud IAP.
Author-email: Viktor Zhemchuzhnikov <asai5909@gmail.com>
Project-URL: Homepage, https://github.com/asai95/fastapi-google-iap
Project-URL: Issues, https://github.com/asai95/fastapi-google-iap/issues
Classifier: Programming Language :: Python :: 3 :: Only
Classifier: Programming Language :: Python :: 3.8
Classifier: Programming Language :: Python :: 3.9
Classifier: Programming Language :: Python :: 3.10
Classifier: Programming Language :: Python :: 3.11
Classifier: Programming Language :: Python :: 3.12
Classifier: License :: OSI Approved :: MIT License
Classifier: Operating System :: OS Independent
Requires-Python: >=3.8
License-File: LICENSE
Requires-Dist: starlette
Requires-Dist: google-auth
Requires-Dist: google-auth-oauthlib
